<?xml version="1.0" encoding="UTF-8"?>
<objects serializationModel="Studio.02.03.00">
	<object class="AudioFile" id="{ce53c9f2-9d0c-4723-8f5c-97cfff087196}">
		<property name="assetPath">
			<value>ExampleAssets/Weapons/Explosion/weapons_explosion_debris_medium.ogg</value>
		</property>
		<property name="frequencyInKHz">
			<value>44.0999985</value>
		</property>
		<property name="channelCount">
			<value>2</value>
		</property>
		<property name="length">
			<value>2.1092970521541949</value>
		</property>
		<relationship name="masterAssetFolder">
			<destination>{7d6a153b-1024-4098-b2b2-b3fa76aa4109}</destination>
		</relationship>
	</object>
</objects>
