<?xml version="1.0" encoding="UTF-8"?>
<objects serializationModel="Studio.02.03.00">
	<object class="AudioFile" id="{fd6fe1d3-d6f7-497f-a6d2-304dd8b863e6}">
		<property name="assetPath">
			<value>ExampleAssets/Vehicles/Car Engine/veh_car_engine_190E_02549.ogg</value>
		</property>
		<property name="frequencyInKHz">
			<value>48</value>
		</property>
		<property name="channelCount">
			<value>1</value>
		</property>
		<property name="length">
			<value>1.0790208333333333</value>
		</property>
		<relationship name="masterAssetFolder">
			<destination>{b0ac71e2-4d27-4e4c-a8bd-bac1614aec5f}</destination>
		</relationship>
	</object>
</objects>
