<?xml version="1.0" encoding="UTF-8"?>
<objects serializationModel="Studio.02.03.00">
	<object class="AudioFile" id="{5608c337-3e4e-4524-be88-1a1e992b40c4}">
		<property name="assetPath">
			<value>ExampleAssets/Vehicles/Car Engine/veh_car_engine_190E_06723.ogg</value>
		</property>
		<property name="frequencyInKHz">
			<value>48</value>
		</property>
		<property name="channelCount">
			<value>1</value>
		</property>
		<property name="length">
			<value>0.51433333333333331</value>
		</property>
		<relationship name="masterAssetFolder">
			<destination>{7d6a153b-1024-4098-b2b2-b3fa76aa4109}</destination>
		</relationship>
	</object>
</objects>
